eventtracer/__init__.py
eventtracer_py-0.0.2.dist-info/LICENSE
eventtracer_py-0.0.2.dist-info/METADATA
eventtracer_py-0.0.2.dist-info/WHEEL
eventtracer_py-0.0.2.dist-info/top_level.txt
eventtracer_py-0.0.2.dist-info/RECORD
