Metadata-Version: 2.1
Name: eventtracer-py
Version: 0.0.2
Summary: A library for tracing code into the chrome Event Trace format
Home-page: https://github.com/shish/eventtracer-py
Author: Shish
Author-email: webmaster@shishnet.org
License: UNKNOWN
Platform: UNKNOWN
Classifier: Programming Language :: Python :: 3
Classifier: License :: OSI Approved :: MIT License
Classifier: Operating System :: OS Independent
Requires-Python: >=3.6
